pivmetalib/__init__.py
pivmetalib/_version.py
pivmetalib/decorator.py
pivmetalib/jsonld.py
pivmetalib/model.py
pivmetalib/namespace.py
pivmetalib/owl.py
pivmetalib/query_util.py
pivmetalib/utils.py
pivmetalib/dcat/__init__.py
pivmetalib/dcat/resource.py
pivmetalib/hdf5/__init__.py
pivmetalib/hdf5/allotrope.py
pivmetalib/m4i/__init__.py
pivmetalib/m4i/processingstep.py
pivmetalib/pivmeta/__init__.py
pivmetalib/pivmeta/distribution.py
pivmetalib/pivmeta/method.py
pivmetalib/pivmeta/pivsetup.py
pivmetalib/pivmeta/processingstep.py
pivmetalib/pivmeta/tool.py
pivmetalib/pivmeta/variable.py
pivmetalib/sd/__init__.py
pivmetalib/sd/software.py
pivmetalib-3.1.0.1.dist-info/licenses/LICENSE.md
pivmetalib-3.1.0.1.dist-info/METADATA
pivmetalib-3.1.0.1.dist-info/WHEEL
pivmetalib-3.1.0.1.dist-info/top_level.txt
pivmetalib-3.1.0.1.dist-info/RECORD
