Metadata-Version: 2.4
Name: pivmetalib
Version: 3.1.0.1
Summary: A Python library for working with the pivmeta ontology.
Author-email: Matthias Probst <matthias.probst@kit.edu>
License-Expression: MIT
Project-URL: Homepage, https://github.com/matthiasprobst/pivmetalib
Keywords: piv,particle-image-velocimetry,ontology,metadata
Classifier: Programming Language :: Python :: 3.9
Classifier: Programming Language :: Python :: 3.10
Classifier: Programming Language :: Python :: 3.11
Classifier: Programming Language :: Python :: 3.12
Classifier: Programming Language :: Python :: 3.13
Classifier: Operating System :: OS Independent
Classifier: Development Status :: 4 - Beta
License-File: LICENSE.md
Requires-Dist: rdflib>=7.0.0
Requires-Dist: appdirs>=1.4.4
Requires-Dist: simplejson>=3.19.2
Requires-Dist: python-dateutil>=2.9.0
Requires-Dist: requests>=2.32.4
Requires-Dist: ontolutils<0.28.0,>=0.27.0
Requires-Dist: ssnolib==2.2.0.3
Provides-Extra: test
Requires-Dist: pytest>=8.4.2; extra == "test"
Requires-Dist: pytest-cov>=5.0.0; extra == "test"
Requires-Dist: pylint>=3.2.6; extra == "test"
Requires-Dist: pyyaml>=6.0.2; extra == "test"
Requires-Dist: xmltodict>=1.0.0; extra == "test"
Requires-Dist: h5rdmtoolbox<3.0.0,>=2.5.4; extra == "test"
Requires-Dist: toml>=0.10.0; extra == "test"
Provides-Extra: complete
Requires-Dist: pivmetalib[test]; extra == "complete"
Dynamic: license-file
